cbt_query/__init__.py
cbt_query/__main__.py
cbt_query/server.py
cbt_query-0.5.0.dist-info/METADATA
cbt_query-0.5.0.dist-info/WHEEL
cbt_query-0.5.0.dist-info/entry_points.txt
cbt_query-0.5.0.dist-info/RECORD
