Metadata-Version: 2.4
Name: cbt-query
Version: 0.5.0
Summary: CBT Query MCP Server with cross-platform support
Project-URL: Homepage, https://github.com/example/cbt-query
Project-URL: Repository, https://github.com/example/cbt-query.git
Project-URL: Documentation, https://github.com/example/cbt-query/blob/main/README.md
Project-URL: Issues, https://github.com/example/cbt-query/issues
Author-email: CBT Team <cbt-team@example.com>
License-Expression: MIT
Keywords: coverage,mcp,query,tensorrt,testing
Classifier: Development Status :: 4 - Beta
Classifier: Intended Audience :: Developers
Classifier: License :: OSI Approved :: MIT License
Classifier: Operating System :: OS Independent
Classifier: Programming Language :: Python :: 3
Classifier: Programming Language :: Python :: 3.10
Classifier: Programming Language :: Python :: 3.11
Classifier: Programming Language :: Python :: 3.12
Classifier: Topic :: Software Development :: Testing
Classifier: Topic :: System :: Monitoring
Requires-Python: >=3.10
Requires-Dist: httpx>=0.24.0
Requires-Dist: mcp[cli]==1.12.0
Requires-Dist: pip>=25.2
Requires-Dist: pydantic<2.9.0,>=2.0.0
Requires-Dist: requests>=2.32.4
Provides-Extra: dev
Requires-Dist: black>=23.0.0; extra == 'dev'
Requires-Dist: isort>=5.12.0; extra == 'dev'
Requires-Dist: mypy>=1.0.0; extra == 'dev'
Requires-Dist: pytest-asyncio>=0.21.0; extra == 'dev'
Requires-Dist: pytest>=7.0.0; extra == 'dev'
